the_spymaster_util/__init__.py
the_spymaster_util/async_task_manager.py
the_spymaster_util/config.py
the_spymaster_util/context_thread.py
the_spymaster_util/http/__init__.py
the_spymaster_util/http/client.py
the_spymaster_util/http/defs.py
the_spymaster_util/http/errors.py
the_spymaster_util/logger.py
the_spymaster_util/measure_time.py
the_spymaster_util/py.typed
the_spymaster_util/strings.py
the_spymaster_util/ttl_dict.py
the_spymaster_util-4.0.0.dist-info/METADATA
the_spymaster_util-4.0.0.dist-info/WHEEL
the_spymaster_util-4.0.0.dist-info/RECORD
